ds4mllib/__init__.py
ds4mllib/attribute.py
ds4mllib/dataset.py
ds4mllib/evaluator.py
ds4mllib/metrics.py
ds4mllib/synthesizer.py
ds4mllib/utils.py
ds4mllib-0.0.3.dist-info/LICENSE
ds4mllib-0.0.3.dist-info/METADATA
ds4mllib-0.0.3.dist-info/WHEEL
ds4mllib-0.0.3.dist-info/top_level.txt
ds4mllib-0.0.3.dist-info/RECORD
